{
  "title": "MemHunt - LEVEL 3",
  "description": "LEVEL 3. It was a quite morning when I was writing the presentation but everything went blue with some white strings printed very quickly. Can you find what has been printed?\n\nAuthor: [@slsanna](https://github.com/slsanna)",
  "authors": [
    "Silvia Lucia Sanna <@slsanna>"
  ],
  "tags": [
    "foren"
  ],
  "hiddenTags": [],
  "order": 0,
  "flags": [
    "^srdnlen\\{0bfuscated_P0W3rSH3lL5cr1pt\\}$"
  ],
  "scoring": {
    "type": "dynamic",
    "start": 500,
    "stop": 50,
    "decay": 30
  },
  "files": [],
  "hints": []
}